Workbook

Sheet Bolsos
A1: SEMZO PRIVÉ — Rentabilidad de la opción de compra por bolso
A2: Celdas amarillas = editables. El resto se recalcula solo. Cambia los supuestos en la pestaña 'Supuestos'.
A4: Bolso | B4: Plan | C4: Cuota (€/mes) | D4: Coste real (€) | E4: Mercado 2ª mano ref. (€) | F4: Precio compra inicial (€) ←EDITAR | G4: Meses hasta ser gratis | H4: Nº cobros hasta entonces | I4: Precio si compra en mes ref. | J4: Total cobrado (cuotas+saldo) | K4: Beneficio bruto (€) | L4: Comisión de cobro est. (€) | M4: Coste de capital est. (€) | N4: Provisión desgaste (€) | O4: Beneficio neto (€) | P4: Margen neto / coste | Q4: Estado precio
A5: Chanel 2.55 Matelassé | B5: Privé | C5: =IF(B5="L'Essentiel",Supuestos!$B$13,IF(B5="Signature",Supuestos!$B$14,IF(B5="Privé",Supuestos!$B$15,"?"))) -> 279 | D5: 1975.72 | E5: 4100 | F5: 4500 | G5: =IF(F5="SOLO ALQUILER","—",F5/(C5*Supuestos!$B$6)) -> 16.129032 | H5: =IF(G5="—","—",ROUNDUP(G5,0)) -> 17 | I5: =IF(F5="SOLO ALQUILER","—",MAX(0,F5-C5*Supuestos!$B$6*Supuestos!$B$7)) -> 2826 | J5: =IF(F5="SOLO ALQUILER","—",F5) -> 4500 | K5: =IF(F5="SOLO ALQUILER","—",F5-D5) -> 2524.28 | L5: =IF(F5="SOLO ALQUILER","—",Supuestos!$B$9*F5+Supuestos!$B$10*H5) -> 71.75 | M5: =IF(F5="SOLO ALQUILER","—",D5*Supuestos!$B$11*(G5/2)/12) -> 132.77688 | N5: =IF(F5="SOLO ALQUILER","—",Supuestos!$B$12*F5) -> 225 | O5: =IF(F5="SOLO ALQUILER","—",K5-L5-M5-N5) -> 2094.7531 | P5: =IF(F5="SOLO ALQUILER","—",O5/D5) -> 1.060248 | Q5: =IF(F5="SOLO ALQUILER","Solo alquiler (sin opción de compra)",IF(F5<D5*1.15,"⚠ Precio bajo: subir precio inicial","OK")) -> OK
A6: Chanel Mini Matelassé | B6: Privé | C6: =IF(B6="L'Essentiel",Supuestos!$B$13,IF(B6="Signature",Supuestos!$B$14,IF(B6="Privé",Supuestos!$B$15,"?"))) -> 279 | D6: 2819.51 | E6: 4400 | F6: 4850 | G6: =IF(F6="SOLO ALQUILER","—",F6/(C6*Supuestos!$B$6)) -> 17.383513 | H6: =IF(G6="—","—",ROUNDUP(G6,0)) -> 18 | I6: =IF(F6="SOLO ALQUILER","—",MAX(0,F6-C6*Supuestos!$B$6*Supuestos!$B$7)) -> 3176 | J6: =IF(F6="SOLO ALQUILER","—",F6) -> 4850 | K6: =IF(F6="SOLO ALQUILER","—",F6-D6) -> 2030.49 | L6: =IF(F6="SOLO ALQUILER","—",Supuestos!$B$9*F6+Supuestos!$B$10*H6) -> 77.25 | M6: =IF(F6="SOLO ALQUILER","—",D6*Supuestos!$B$11*(G6/2)/12) -> 204.22078 | N6: =IF(F6="SOLO ALQUILER","—",Supuestos!$B$12*F6) -> 242.5 | O6: =IF(F6="SOLO ALQUILER","—",K6-L6-M6-N6) -> 1506.5192 | P6: =IF(F6="SOLO ALQUILER","—",O6/D6) -> 0.53431952 | Q6: =IF(F6="SOLO ALQUILER","Solo alquiler (sin opción de compra)",IF(F6<D6*1.15,"⚠ Precio bajo: subir precio inicial","OK")) -> OK
A7: Fendi Mini Peekaboo | B7: Privé | C7: =IF(B7="L'Essentiel",Supuestos!$B$13,IF(B7="Signature",Supuestos!$B$14,IF(B7="Privé",Supuestos!$B$15,"?"))) -> 279 | D7: 1466.99 | E7: 2430 | F7: 2650 | G7: =IF(F7="SOLO ALQUILER","—",F7/(C7*Supuestos!$B$6)) -> 9.4982079 | H7: =IF(G7="—","—",ROUNDUP(G7,0)) -> 10 | I7: =IF(F7="SOLO ALQUILER","—",MAX(0,F7-C7*Supuestos!$B$6*Supuestos!$B$7)) -> 976 | J7: =IF(F7="SOLO ALQUILER","—",F7) -> 2650 | K7: =IF(F7="SOLO ALQUILER","—",F7-D7) -> 1183.01 | L7: =IF(F7="SOLO ALQUILER","—",Supuestos!$B$9*F7+Supuestos!$B$10*H7) -> 42.25 | M7: =IF(F7="SOLO ALQUILER","—",D7*Supuestos!$B$11*(G7/2)/12) -> 58.0574 | N7: =IF(F7="SOLO ALQUILER","—",Supuestos!$B$12*F7) -> 132.5 | O7: =IF(F7="SOLO ALQUILER","—",K7-L7-M7-N7) -> 950.2026 | P7: =IF(F7="SOLO ALQUILER","—",O7/D7) -> 0.64772262 | Q7: =IF(F7="SOLO ALQUILER","Solo alquiler (sin opción de compra)",IF(F7<D7*1.15,"⚠ Precio bajo: subir precio inicial","OK")) -> OK
A8: Gucci Jackie Burdeos | B8: Privé | C8: =IF(B8="L'Essentiel",Supuestos!$B$13,IF(B8="Signature",Supuestos!$B$14,IF(B8="Privé",Supuestos!$B$15,"?"))) -> 279 | D8: 1404.59 | E8: s/d | F8: 2200 | G8: =IF(F8="SOLO ALQUILER","—",F8/(C8*Supuestos!$B$6)) -> 7.8853047 | H8: =IF(G8="—","—",ROUNDUP(G8,0)) -> 8 | I8: =IF(F8="SOLO ALQUILER","—",MAX(0,F8-C8*Supuestos!$B$6*Supuestos!$B$7)) -> 526 | J8: =IF(F8="SOLO ALQUILER","—",F8) -> 2200 | K8: =IF(F8="SOLO ALQUILER","—",F8-D8) -> 795.41 | L8: =IF(F8="SOLO ALQUILER","—",Supuestos!$B$9*F8+Supuestos!$B$10*H8) -> 35 | M8: =IF(F8="SOLO ALQUILER","—",D8*Supuestos!$B$11*(G8/2)/12) -> 46.148417 | N8: =IF(F8="SOLO ALQUILER","—",Supuestos!$B$12*F8) -> 110 | O8: =IF(F8="SOLO ALQUILER","—",K8-L8-M8-N8) -> 604.26158 | P8: =IF(F8="SOLO ALQUILER","—",O8/D8) -> 0.43020496 | Q8: =IF(F8="SOLO ALQUILER","Solo alquiler (sin opción de compra)",IF(F8<D8*1.15,"⚠ Precio bajo: subir precio inicial","OK")) -> OK
A9: Chanel Sequin V-Stitch Clutch | B9: Privé | C9: =IF(B9="L'Essentiel",Supuestos!$B$13,IF(B9="Signature",Supuestos!$B$14,IF(B9="Privé",Supuestos!$B$15,"?"))) -> 279 | D9: 699.46 | E9: s/d | F9: 1100 | G9: =IF(F9="SOLO ALQUILER","—",F9/(C9*Supuestos!$B$6)) -> 3.9426523 | H9: =IF(G9="—","—",ROUNDUP(G9,0)) -> 4 | I9: =IF(F9="SOLO ALQUILER","—",MAX(0,F9-C9*Supuestos!$B$6*Supuestos!$B$7)) -> 0 | J9: =IF(F9="SOLO ALQUILER","—",F9) -> 1100 | K9: =IF(F9="SOLO ALQUILER","—",F9-D9) -> 400.54 | L9: =IF(F9="SOLO ALQUILER","—",Supuestos!$B$9*F9+Supuestos!$B$10*H9) -> 17.5 | M9: =IF(F9="SOLO ALQUILER","—",D9*Supuestos!$B$11*(G9/2)/12) -> 11.490532 | N9: =IF(F9="SOLO ALQUILER","—",Supuestos!$B$12*F9) -> 55 | O9: =IF(F9="SOLO ALQUILER","—",K9-L9-M9-N9) -> 316.54947 | P9: =IF(F9="SOLO ALQUILER","—",O9/D9) -> 0.45256265 | Q9: =IF(F9="SOLO ALQUILER","Solo alquiler (sin opción de compra)",IF(F9<D9*1.15,"⚠ Precio bajo: subir precio inicial","OK")) -> OK
A10: Chanel WOC (Crossbody) | B10: Privé | C10: =IF(B10="L'Essentiel",Supuestos!$B$13,IF(B10="Signature",Supuestos!$B$14,IF(B10="Privé",Supuestos!$B$15,"?"))) -> 279 | D10: 2255 | E10: 2450 | F10: 2700 | G10: =IF(F10="SOLO ALQUILER","—",F10/(C10*Supuestos!$B$6)) -> 9.6774194 | H10: =IF(G10="—","—",ROUNDUP(G10,0)) -> 10 | I10: =IF(F10="SOLO ALQUILER","—",MAX(0,F10-C10*Supuestos!$B$6*Supuestos!$B$7)) -> 1026 | J10: =IF(F10="SOLO ALQUILER","—",F10) -> 2700 | K10: =IF(F10="SOLO ALQUILER","—",F10-D10) -> 445 | L10: =IF(F10="SOLO ALQUILER","—",Supuestos!$B$9*F10+Supuestos!$B$10*H10) -> 43 | M10: =IF(F10="SOLO ALQUILER","—",D10*Supuestos!$B$11*(G10/2)/12) -> 90.927419 | N10: =IF(F10="SOLO ALQUILER","—",Supuestos!$B$12*F10) -> 135 | O10: =IF(F10="SOLO ALQUILER","—",K10-L10-M10-N10) -> 176.07258 | P10: =IF(F10="SOLO ALQUILER","—",O10/D10) -> 0.078080967 | Q10: =IF(F10="SOLO ALQUILER","Solo alquiler (sin opción de compra)",IF(F10<D10*1.15,"⚠ Precio bajo: subir precio inicial","OK")) -> OK
A11: Fendi Baguette | B11: Privé | C11: =IF(B11="L'Essentiel",Supuestos!$B$13,IF(B11="Signature",Supuestos!$B$14,IF(B11="Privé",Supuestos!$B$15,"?"))) -> 279 | D11: 1778.09 | E11: 1765 | F11: 1950 | G11: =IF(F11="SOLO ALQUILER","—",F11/(C11*Supuestos!$B$6)) -> 6.9892473 | H11: =IF(G11="—","—",ROUNDUP(G11,0)) -> 7 | I11: =IF(F11="SOLO ALQUILER","—",MAX(0,F11-C11*Supuestos!$B$6*Supuestos!$B$7)) -> 276 | J11: =IF(F11="SOLO ALQUILER","—",F11) -> 1950 | K11: =IF(F11="SOLO ALQUILER","—",F11-D11) -> 171.91 | L11: =IF(F11="SOLO ALQUILER","—",Supuestos!$B$9*F11+Supuestos!$B$10*H11) -> 31 | M11: =IF(F11="SOLO ALQUILER","—",D11*Supuestos!$B$11*(G11/2)/12) -> 51.781295 | N11: =IF(F11="SOLO ALQUILER","—",Supuestos!$B$12*F11) -> 97.5 | O11: =IF(F11="SOLO ALQUILER","—",K11-L11-M11-N11) -> -8.3712948 | P11: =IF(F11="SOLO ALQUILER","—",O11/D11) -> -0.0047080265 | Q11: =IF(F11="SOLO ALQUILER","Solo alquiler (sin opción de compra)",IF(F11<D11*1.15,"⚠ Precio bajo: subir precio inicial","OK")) -> ⚠ Precio bajo: subir precio inicial
A12: YSL College | B12: Privé | C12: =IF(B12="L'Essentiel",Supuestos!$B$13,IF(B12="Signature",Supuestos!$B$14,IF(B12="Privé",Supuestos!$B$15,"?"))) -> 279 | D12: 1090.9 | E12: 1330 | F12: 1450 | G12: =IF(F12="SOLO ALQUILER","—",F12/(C12*Supuestos!$B$6)) -> 5.1971326 | H12: =IF(G12="—","—",ROUNDUP(G12,0)) -> 6 | I12: =IF(F12="SOLO ALQUILER","—",MAX(0,F12-C12*Supuestos!$B$6*Supuestos!$B$7)) -> 0 | J12: =IF(F12="SOLO ALQUILER","—",F12) -> 1450 | K12: =IF(F12="SOLO ALQUILER","—",F12-D12) -> 359.1 | L12: =IF(F12="SOLO ALQUILER","—",Supuestos!$B$9*F12+Supuestos!$B$10*H12) -> 23.25 | M12: =IF(F12="SOLO ALQUILER","—",D12*Supuestos!$B$11*(G12/2)/12) -> 23.623133 | N12: =IF(F12="SOLO ALQUILER","—",Supuestos!$B$12*F12) -> 72.5 | O12: =IF(F12="SOLO ALQUILER","—",K12-L12-M12-N12) -> 239.72687 | P12: =IF(F12="SOLO ALQUILER","—",O12/D12) -> 0.21975146 | Q12: =IF(F12="SOLO ALQUILER","Solo alquiler (sin opción de compra)",IF(F12<D12*1.15,"⚠ Precio bajo: subir precio inicial","OK")) -> OK
A13: Gucci Bamboo 1947 | B13: Signature | C13: =IF(B13="L'Essentiel",Supuestos!$B$13,IF(B13="Signature",Supuestos!$B$14,IF(B13="Privé",Supuestos!$B$15,"?"))) -> 149 | D13: 1092 | E13: 1450 | F13: 1600 | G13: =IF(F13="SOLO ALQUILER","—",F13/(C13*Supuestos!$B$6)) -> 10.738255 | H13: =IF(G13="—","—",ROUNDUP(G13,0)) -> 11 | I13: =IF(F13="SOLO ALQUILER","—",MAX(0,F13-C13*Supuestos!$B$6*Supuestos!$B$7)) -> 706 | J13: =IF(F13="SOLO ALQUILER","—",F13) -> 1600 | K13: =IF(F13="SOLO ALQUILER","—",F13-D13) -> 508 | L13: =IF(F13="SOLO ALQUILER","—",Supuestos!$B$9*F13+Supuestos!$B$10*H13) -> 26.75 | M13: =IF(F13="SOLO ALQUILER","—",D13*Supuestos!$B$11*(G13/2)/12) -> 48.85906 | N13: =IF(F13="SOLO ALQUILER","—",Supuestos!$B$12*F13) -> 80 | O13: =IF(F13="SOLO ALQUILER","—",K13-L13-M13-N13) -> 352.39094 | P13: =IF(F13="SOLO ALQUILER","—",O13/D13) -> 0.32270233 | Q13: =IF(F13="SOLO ALQUILER","Solo alquiler (sin opción de compra)",IF(F13<D13*1.15,"⚠ Precio bajo: subir precio inicial","OK")) -> OK
A14: YSL Envelope | B14: Signature | C14: =IF(B14="L'Essentiel",Supuestos!$B$13,IF(B14="Signature",Supuestos!$B$14,IF(B14="Privé",Supuestos!$B$15,"?"))) -> 149 | D14: 1052.18 | E14: 1050 | F14: 1150 | G14: =IF(F14="SOLO ALQUILER","—",F14/(C14*Supuestos!$B$6)) -> 7.7181208 | H14: =IF(G14="—","—",ROUNDUP(G14,0)) -> 8 | I14: =IF(F14="SOLO ALQUILER","—",MAX(0,F14-C14*Supuestos!$B$6*Supuestos!$B$7)) -> 256 | J14: =IF(F14="SOLO ALQUILER","—",F14) -> 1150 | K14: =IF(F14="SOLO ALQUILER","—",F14-D14) -> 97.82 | L14: =IF(F14="SOLO ALQUILER","—",Supuestos!$B$9*F14+Supuestos!$B$10*H14) -> 19.25 | M14: =IF(F14="SOLO ALQUILER","—",D14*Supuestos!$B$11*(G14/2)/12) -> 33.836885 | N14: =IF(F14="SOLO ALQUILER","—",Supuestos!$B$12*F14) -> 57.5 | O14: =IF(F14="SOLO ALQUILER","—",K14-L14-M14-N14) -> -12.766885 | P14: =IF(F14="SOLO ALQUILER","—",O14/D14) -> -0.012133746 | Q14: =IF(F14="SOLO ALQUILER","Solo alquiler (sin opción de compra)",IF(F14<D14*1.15,"⚠ Precio bajo: subir precio inicial","OK")) -> ⚠ Precio bajo: subir precio inicial
A15: Louis Vuitton Pont Neuf | B15: Signature | C15: =IF(B15="L'Essentiel",Supuestos!$B$13,IF(B15="Signature",Supuestos!$B$14,IF(B15="Privé",Supuestos!$B$15,"?"))) -> 149 | D15: 773.7 | E15: 880 | F15: 950 | G15: =IF(F15="SOLO ALQUILER","—",F15/(C15*Supuestos!$B$6)) -> 6.3758389 | H15: =IF(G15="—","—",ROUNDUP(G15,0)) -> 7 | I15: =IF(F15="SOLO ALQUILER","—",MAX(0,F15-C15*Supuestos!$B$6*Supuestos!$B$7)) -> 56 | J15: =IF(F15="SOLO ALQUILER","—",F15) -> 950 | K15: =IF(F15="SOLO ALQUILER","—",F15-D15) -> 176.3 | L15: =IF(F15="SOLO ALQUILER","—",Supuestos!$B$9*F15+Supuestos!$B$10*H15) -> 16 | M15: =IF(F15="SOLO ALQUILER","—",D15*Supuestos!$B$11*(G15/2)/12) -> 20.554111 | N15: =IF(F15="SOLO ALQUILER","—",Supuestos!$B$12*F15) -> 47.5 | O15: =IF(F15="SOLO ALQUILER","—",K15-L15-M15-N15) -> 92.245889 | P15: =IF(F15="SOLO ALQUILER","—",O15/D15) -> 0.11922695 | Q15: =IF(F15="SOLO ALQUILER","Solo alquiler (sin opción de compra)",IF(F15<D15*1.15,"⚠ Precio bajo: subir precio inicial","OK")) -> OK
A16: Louis Vuitton Rêverie | B16: Signature | C16: =IF(B16="L'Essentiel",Supuestos!$B$13,IF(B16="Signature",Supuestos!$B$14,IF(B16="Privé",Supuestos!$B$15,"?"))) -> 149 | D16: 708.1 | E16: s/d | F16: 1100 | G16: =IF(F16="SOLO ALQUILER","—",F16/(C16*Supuestos!$B$6)) -> 7.3825503 | H16: =IF(G16="—","—",ROUNDUP(G16,0)) -> 8 | I16: =IF(F16="SOLO ALQUILER","—",MAX(0,F16-C16*Supuestos!$B$6*Supuestos!$B$7)) -> 206 | J16: =IF(F16="SOLO ALQUILER","—",F16) -> 1100 | K16: =IF(F16="SOLO ALQUILER","—",F16-D16) -> 391.9 | L16: =IF(F16="SOLO ALQUILER","—",Supuestos!$B$9*F16+Supuestos!$B$10*H16) -> 18.5 | M16: =IF(F16="SOLO ALQUILER","—",D16*Supuestos!$B$11*(G16/2)/12) -> 21.7816 | N16: =IF(F16="SOLO ALQUILER","—",Supuestos!$B$12*F16) -> 55 | O16: =IF(F16="SOLO ALQUILER","—",K16-L16-M16-N16) -> 296.6184 | P16: =IF(F16="SOLO ALQUILER","—",O16/D16) -> 0.41889338 | Q16: =IF(F16="SOLO ALQUILER","Solo alquiler (sin opción de compra)",IF(F16<D16*1.15,"⚠ Precio bajo: subir precio inicial","OK")) -> OK
A17: Louis Vuitton Portefeuille Bicolor | B17: Signature | C17: =IF(B17="L'Essentiel",Supuestos!$B$13,IF(B17="Signature",Supuestos!$B$14,IF(B17="Privé",Supuestos!$B$15,"?"))) -> 149 | D17: 497.4 | E17: s/d | F17: 750 | G17: =IF(F17="SOLO ALQUILER","—",F17/(C17*Supuestos!$B$6)) -> 5.033557 | H17: =IF(G17="—","—",ROUNDUP(G17,0)) -> 6 | I17: =IF(F17="SOLO ALQUILER","—",MAX(0,F17-C17*Supuestos!$B$6*Supuestos!$B$7)) -> 0 | J17: =IF(F17="SOLO ALQUILER","—",F17) -> 750 | K17: =IF(F17="SOLO ALQUILER","—",F17-D17) -> 252.6 | L17: =IF(F17="SOLO ALQUILER","—",Supuestos!$B$9*F17+Supuestos!$B$10*H17) -> 12.75 | M17: =IF(F17="SOLO ALQUILER","—",D17*Supuestos!$B$11*(G17/2)/12) -> 10.432047 | N17: =IF(F17="SOLO ALQUILER","—",Supuestos!$B$12*F17) -> 37.5 | O17: =IF(F17="SOLO ALQUILER","—",K17-L17-M17-N17) -> 191.91795 | P17: =IF(F17="SOLO ALQUILER","—",O17/D17) -> 0.38584229 | Q17: =IF(F17="SOLO ALQUILER","Solo alquiler (sin opción de compra)",IF(F17<D17*1.15,"⚠ Precio bajo: subir precio inicial","OK")) -> OK
A18: Louis Vuitton Amarillo (Malesherbes) | B18: Signature | C18: =IF(B18="L'Essentiel",Supuestos!$B$13,IF(B18="Signature",Supuestos!$B$14,IF(B18="Privé",Supuestos!$B$15,"?"))) -> 149 | D18: 433.7 | E18: s/d | F18: 650 | G18: =IF(F18="SOLO ALQUILER","—",F18/(C18*Supuestos!$B$6)) -> 4.3624161 | H18: =IF(G18="—","—",ROUNDUP(G18,0)) -> 5 | I18: =IF(F18="SOLO ALQUILER","—",MAX(0,F18-C18*Supuestos!$B$6*Supuestos!$B$7)) -> 0 | J18: =IF(F18="SOLO ALQUILER","—",F18) -> 650 | K18: =IF(F18="SOLO ALQUILER","—",F18-D18) -> 216.3 | L18: =IF(F18="SOLO ALQUILER","—",Supuestos!$B$9*F18+Supuestos!$B$10*H18) -> 11 | M18: =IF(F18="SOLO ALQUILER","—",D18*Supuestos!$B$11*(G18/2)/12) -> 7.8832494 | N18: =IF(F18="SOLO ALQUILER","—",Supuestos!$B$12*F18) -> 32.5 | O18: =IF(F18="SOLO ALQUILER","—",K18-L18-M18-N18) -> 164.91675 | P18: =IF(F18="SOLO ALQUILER","—",O18/D18) -> 0.38025536 | Q18: =IF(F18="SOLO ALQUILER","Solo alquiler (sin opción de compra)",IF(F18<D18*1.15,"⚠ Precio bajo: subir precio inicial","OK")) -> OK
A19: Prada Granulada | B19: Signature | C19: =IF(B19="L'Essentiel",Supuestos!$B$13,IF(B19="Signature",Supuestos!$B$14,IF(B19="Privé",Supuestos!$B$15,"?"))) -> 149 | D19: 1322 | E19: s/d | F19: 2050 | G19: =IF(F19="SOLO ALQUILER","—",F19/(C19*Supuestos!$B$6)) -> 13.758389 | H19: =IF(G19="—","—",ROUNDUP(G19,0)) -> 14 | I19: =IF(F19="SOLO ALQUILER","—",MAX(0,F19-C19*Supuestos!$B$6*Supuestos!$B$7)) -> 1156 | J19: =IF(F19="SOLO ALQUILER","—",F19) -> 2050 | K19: =IF(F19="SOLO ALQUILER","—",F19-D19) -> 728 | L19: =IF(F19="SOLO ALQUILER","—",Supuestos!$B$9*F19+Supuestos!$B$10*H19) -> 34.25 | M19: =IF(F19="SOLO ALQUILER","—",D19*Supuestos!$B$11*(G19/2)/12) -> 75.785794 | N19: =IF(F19="SOLO ALQUILER","—",Supuestos!$B$12*F19) -> 102.5 | O19: =IF(F19="SOLO ALQUILER","—",K19-L19-M19-N19) -> 515.46421 | P19: =IF(F19="SOLO ALQUILER","—",O19/D19) -> 0.38991241 | Q19: =IF(F19="SOLO ALQUILER","Solo alquiler (sin opción de compra)",IF(F19<D19*1.15,"⚠ Precio bajo: subir precio inicial","OK")) -> OK
A20: Prada Saffiano | B20: Signature | C20: =IF(B20="L'Essentiel",Supuestos!$B$13,IF(B20="Signature",Supuestos!$B$14,IF(B20="Privé",Supuestos!$B$15,"?"))) -> 149 | D20: 1206.43 | E20: s/d | F20: 1850 | G20: =IF(F20="SOLO ALQUILER","—",F20/(C20*Supuestos!$B$6)) -> 12.416107 | H20: =IF(G20="—","—",ROUNDUP(G20,0)) -> 13 | I20: =IF(F20="SOLO ALQUILER","—",MAX(0,F20-C20*Supuestos!$B$6*Supuestos!$B$7)) -> 956 | J20: =IF(F20="SOLO ALQUILER","—",F20) -> 1850 | K20: =IF(F20="SOLO ALQUILER","—",F20-D20) -> 643.57 | L20: =IF(F20="SOLO ALQUILER","—",Supuestos!$B$9*F20+Supuestos!$B$10*H20) -> 31 | M20: =IF(F20="SOLO ALQUILER","—",D20*Supuestos!$B$11*(G20/2)/12) -> 62.413185 | N20: =IF(F20="SOLO ALQUILER","—",Supuestos!$B$12*F20) -> 92.5 | O20: =IF(F20="SOLO ALQUILER","—",K20-L20-M20-N20) -> 457.65681 | P20: =IF(F20="SOLO ALQUILER","—",O20/D20) -> 0.37934801 | Q20: =IF(F20="SOLO ALQUILER","Solo alquiler (sin opción de compra)",IF(F20<D20*1.15,"⚠ Precio bajo: subir precio inicial","OK")) -> OK
A21: Marni Trunk Mini | B21: L'Essentiel | C21: =IF(B21="L'Essentiel",Supuestos!$B$13,IF(B21="Signature",Supuestos!$B$14,IF(B21="Privé",Supuestos!$B$15,"?"))) -> 59 | D21: 583.1 | E21: 480 | F21: 800 | G21: =IF(F21="SOLO ALQUILER","—",F21/(C21*Supuestos!$B$6)) -> 13.559322 | H21: =IF(G21="—","—",ROUNDUP(G21,0)) -> 14 | I21: =IF(F21="SOLO ALQUILER","—",MAX(0,F21-C21*Supuestos!$B$6*Supuestos!$B$7)) -> 446 | J21: =IF(F21="SOLO ALQUILER","—",F21) -> 800 | K21: =IF(F21="SOLO ALQUILER","—",F21-D21) -> 216.9 | L21: =IF(F21="SOLO ALQUILER","—",Supuestos!$B$9*F21+Supuestos!$B$10*H21) -> 15.5 | M21: =IF(F21="SOLO ALQUILER","—",D21*Supuestos!$B$11*(G21/2)/12) -> 32.943503 | N21: =IF(F21="SOLO ALQUILER","—",Supuestos!$B$12*F21) -> 40 | O21: =IF(F21="SOLO ALQUILER","—",K21-L21-M21-N21) -> 128.4565 | P21: =IF(F21="SOLO ALQUILER","—",O21/D21) -> 0.22029926 | Q21: =IF(F21="SOLO ALQUILER","Solo alquiler (sin opción de compra)",IF(F21<D21*1.15,"⚠ Precio bajo: subir precio inicial","OK")) -> OK
A22: Marni Tribeca | B22: L'Essentiel | C22: =IF(B22="L'Essentiel",Supuestos!$B$13,IF(B22="Signature",Supuestos!$B$14,IF(B22="Privé",Supuestos!$B$15,"?"))) -> 59 | D22: 448.46 | E22: s/d | F22: 700 | G22: =IF(F22="SOLO ALQUILER","—",F22/(C22*Supuestos!$B$6)) -> 11.864407 | H22: =IF(G22="—","—",ROUNDUP(G22,0)) -> 12 | I22: =IF(F22="SOLO ALQUILER","—",MAX(0,F22-C22*Supuestos!$B$6*Supuestos!$B$7)) -> 346 | J22: =IF(F22="SOLO ALQUILER","—",F22) -> 700 | K22: =IF(F22="SOLO ALQUILER","—",F22-D22) -> 251.54 | L22: =IF(F22="SOLO ALQUILER","—",Supuestos!$B$9*F22+Supuestos!$B$10*H22) -> 13.5 | M22: =IF(F22="SOLO ALQUILER","—",D22*Supuestos!$B$11*(G22/2)/12) -> 22.169633 | N22: =IF(F22="SOLO ALQUILER","—",Supuestos!$B$12*F22) -> 35 | O22: =IF(F22="SOLO ALQUILER","—",K22-L22-M22-N22) -> 180.87037 | P22: =IF(F22="SOLO ALQUILER","—",O22/D22) -> 0.40331438 | Q22: =IF(F22="SOLO ALQUILER","Solo alquiler (sin opción de compra)",IF(F22<D22*1.15,"⚠ Precio bajo: subir precio inicial","OK")) -> OK
A23: Patou Beige | B23: L'Essentiel | C23: =IF(B23="L'Essentiel",Supuestos!$B$13,IF(B23="Signature",Supuestos!$B$14,IF(B23="Privé",Supuestos!$B$15,"?"))) -> 59 | D23: 310.38 | E23: s/d | F23: 500 | G23: =IF(F23="SOLO ALQUILER","—",F23/(C23*Supuestos!$B$6)) -> 8.4745763 | H23: =IF(G23="—","—",ROUNDUP(G23,0)) -> 9 | I23: =IF(F23="SOLO ALQUILER","—",MAX(0,F23-C23*Supuestos!$B$6*Supuestos!$B$7)) -> 146 | J23: =IF(F23="SOLO ALQUILER","—",F23) -> 500 | K23: =IF(F23="SOLO ALQUILER","—",F23-D23) -> 189.62 | L23: =IF(F23="SOLO ALQUILER","—",Supuestos!$B$9*F23+Supuestos!$B$10*H23) -> 9.75 | M23: =IF(F23="SOLO ALQUILER","—",D23*Supuestos!$B$11*(G23/2)/12) -> 10.959746 | N23: =IF(F23="SOLO ALQUILER","—",Supuestos!$B$12*F23) -> 25 | O23: =IF(F23="SOLO ALQUILER","—",K23-L23-M23-N23) -> 143.91025 | P23: =IF(F23="SOLO ALQUILER","—",O23/D23) -> 0.46365827 | Q23: =IF(F23="SOLO ALQUILER","Solo alquiler (sin opción de compra)",IF(F23<D23*1.15,"⚠ Precio bajo: subir precio inicial","OK")) -> OK
A24: Furla Denim | B24: L'Essentiel | C24: =IF(B24="L'Essentiel",Supuestos!$B$13,IF(B24="Signature",Supuestos!$B$14,IF(B24="Privé",Supuestos!$B$15,"?"))) -> 59 | D24: 156.14 | E24: s/d | F24: SOLO ALQUILER | G24: =IF(F24="SOLO ALQUILER","—",F24/(C24*Supuestos!$B$6)) -> — | H24: =IF(G24="—","—",ROUNDUP(G24,0)) -> — | I24: =IF(F24="SOLO ALQUILER","—",MAX(0,F24-C24*Supuestos!$B$6*Supuestos!$B$7)) -> — | J24: =IF(F24="SOLO ALQUILER","—",F24) -> — | K24: =IF(F24="SOLO ALQUILER","—",F24-D24) -> — | L24: =IF(F24="SOLO ALQUILER","—",Supuestos!$B$9*F24+Supuestos!$B$10*H24) -> — | M24: =IF(F24="SOLO ALQUILER","—",D24*Supuestos!$B$11*(G24/2)/12) -> — | N24: =IF(F24="SOLO ALQUILER","—",Supuestos!$B$12*F24) -> — | O24: =IF(F24="SOLO ALQUILER","—",K24-L24-M24-N24) -> — | P24: =IF(F24="SOLO ALQUILER","—",O24/D24) -> — | Q24: =IF(F24="SOLO ALQUILER","Solo alquiler (sin opción de compra)",IF(F24<D24*1.15,"⚠ Precio bajo: subir precio inicial","OK")) -> Solo alquiler (sin opción de compra)
A25: Furla Club Mini | B25: L'Essentiel | C25: =IF(B25="L'Essentiel",Supuestos!$B$13,IF(B25="Signature",Supuestos!$B$14,IF(B25="Privé",Supuestos!$B$15,"?"))) -> 59 | D25: 146.61 | E25: s/d | F25: SOLO ALQUILER | G25: =IF(F25="SOLO ALQUILER","—",F25/(C25*Supuestos!$B$6)) -> — | H25: =IF(G25="—","—",ROUNDUP(G25,0)) -> — | I25: =IF(F25="SOLO ALQUILER","—",MAX(0,F25-C25*Supuestos!$B$6*Supuestos!$B$7)) -> — | J25: =IF(F25="SOLO ALQUILER","—",F25) -> — | K25: =IF(F25="SOLO ALQUILER","—",F25-D25) -> — | L25: =IF(F25="SOLO ALQUILER","—",Supuestos!$B$9*F25+Supuestos!$B$10*H25) -> — | M25: =IF(F25="SOLO ALQUILER","—",D25*Supuestos!$B$11*(G25/2)/12) -> — | N25: =IF(F25="SOLO ALQUILER","—",Supuestos!$B$12*F25) -> — | O25: =IF(F25="SOLO ALQUILER","—",K25-L25-M25-N25) -> — | P25: =IF(F25="SOLO ALQUILER","—",O25/D25) -> — | Q25: =IF(F25="SOLO ALQUILER","Solo alquiler (sin opción de compra)",IF(F25<D25*1.15,"⚠ Precio bajo: subir precio inicial","OK")) -> Solo alquiler (sin opción de compra)
A26: Karl Lagerfeld K/Studio | B26: L'Essentiel | C26: =IF(B26="L'Essentiel",Supuestos!$B$13,IF(B26="Signature",Supuestos!$B$14,IF(B26="Privé",Supuestos!$B$15,"?"))) -> 59 | D26: 449 | E26: s/d | F26: SOLO ALQUILER | G26: =IF(F26="SOLO ALQUILER","—",F26/(C26*Supuestos!$B$6)) -> — | H26: =IF(G26="—","—",ROUNDUP(G26,0)) -> — | I26: =IF(F26="SOLO ALQUILER","—",MAX(0,F26-C26*Supuestos!$B$6*Supuestos!$B$7)) -> — | J26: =IF(F26="SOLO ALQUILER","—",F26) -> — | K26: =IF(F26="SOLO ALQUILER","—",F26-D26) -> — | L26: =IF(F26="SOLO ALQUILER","—",Supuestos!$B$9*F26+Supuestos!$B$10*H26) -> — | M26: =IF(F26="SOLO ALQUILER","—",D26*Supuestos!$B$11*(G26/2)/12) -> — | N26: =IF(F26="SOLO ALQUILER","—",Supuestos!$B$12*F26) -> — | O26: =IF(F26="SOLO ALQUILER","—",K26-L26-M26-N26) -> — | P26: =IF(F26="SOLO ALQUILER","—",O26/D26) -> — | Q26: =IF(F26="SOLO ALQUILER","Solo alquiler (sin opción de compra)",IF(F26<D26*1.15,"⚠ Precio bajo: subir precio inicial","OK")) -> Solo alquiler (sin opción de compra)
A28: TOTAL (bolsos con opción de compra) | D28: =SUMIF(F5:F26,"<>SOLO ALQUILER",D5:D26) -> 21917.71 | F28: =SUMIF(F5:F26,"<>SOLO ALQUILER",F5:F26) -> 33500 | K28: =SUM(K5:K26) -> 11582.29 | O28: =SUM(O5:O26) -> 8391.3953 | P28: =O28/D28 -> 0.38285913
A30: Por plan
A31: Plan | B31: Nº bolsos c/ opción | C31: Coste total | D31: Precio inicial total | E31: Beneficio neto total | F31: Margen neto
A32: L'Essentiel | B32: =COUNTIFS(B5:B26,A32,F5:F26,"<>SOLO ALQUILER") -> 3 | C32: =SUMIFS(D5:D26,B5:B26,A32,F5:F26,"<>SOLO ALQUILER") -> 1341.94 | D32: =SUMIFS(F5:F26,B5:B26,A32,F5:F26,"<>SOLO ALQUILER") -> 2000 | E32: =SUMIFS(O5:O26,B5:B26,A32,F5:F26,"<>SOLO ALQUILER") -> 453.23712 | F32: =E32/C32 -> 0.33774768
A33: Signature | B33: =COUNTIFS(B5:B26,A33,F5:F26,"<>SOLO ALQUILER") -> 8 | C33: =SUMIFS(D5:D26,B5:B26,A33,F5:F26,"<>SOLO ALQUILER") -> 7085.51 | D33: =SUMIFS(F5:F26,B5:B26,A33,F5:F26,"<>SOLO ALQUILER") -> 10100 | E33: =SUMIFS(O5:O26,B5:B26,A33,F5:F26,"<>SOLO ALQUILER") -> 2058.4441 | F33: =E33/C33 -> 0.2905146
A34: Privé | B34: =COUNTIFS(B5:B26,A34,F5:F26,"<>SOLO ALQUILER") -> 8 | C34: =SUMIFS(D5:D26,B5:B26,A34,F5:F26,"<>SOLO ALQUILER") -> 13490.26 | D34: =SUMIFS(F5:F26,B5:B26,A34,F5:F26,"<>SOLO ALQUILER") -> 21400 | E34: =SUMIFS(O5:O26,B5:B26,A34,F5:F26,"<>SOLO ALQUILER") -> 5879.7141 | F34: =E34/C34 -> 0.43584884
A37: Cómo usarlo:
A38: 1) Edita 'Precio compra inicial' (col. F, amarillo) para cada bolso — es el único dato que tienes que tocar bolso a bolso.
A39: 2) Cambia los supuestos generales (% de la cuota, comisiones, coste de capital, provisión) en la pestaña 'Supuestos'.
A40: 3) 'Beneficio neto' y 'Margen neto' se recalculan solos. 'Estado precio' avisa en rojo si el precio inicial no cubre el coste + 15%.
A41: 4) Furla Denim, Furla Club Mini y Karl Lagerfeld K/Studio están marcados 'SOLO ALQUILER': su coste no deja margen suficiente para ofrecer opción de compra.
A42: 5) Todos los cálculos son antes de IVA. Confirma con tu gestor si aplica el régimen REBU de bienes usados.

Sheet Supuestos
A1: SEMZO PRIVÉ — Supuestos de la calculadora de opción de compra
A3: Edita solo las celdas amarillas. Todo lo demás se recalcula solo.
A5: Parámetro | B5: Valor | C5: Nota
A6: % de la cuota que se descuenta del precio de compra (k) | B6: 1 | C6: Confirmado por Erika: el 100% de cada cuota pagada cuenta para la compra.
A7: Mes de referencia para ver el precio 'a mitad de camino' | B7: 6 | C7: Solo para mostrar una foto intermedia en la tabla (ej. precio si compra en el mes 6).
A8: Multiplicador sobre precio de mercado de 2ª mano | B8: 1.1 | C8: Precio de compra inicial recomendado = mercado de 2ª mano x este multiplicador.
A9: Comisión de cobro variable (Stripe/SEPA, %) | B9: 0.015 | C9: Supuesto. Ajusta a tu procesador real.
A10: Comisión de cobro fija por cobro (€) | B10: 0.25 | C10: Supuesto por cargo/mes cobrado.
A11: Coste de capital anual (%) | B11: 0.1 | C11: Coste de oportunidad de tener el bolso comprado como stock mientras se paga.
A12: Provisión por desgaste / impago (% del precio de compra) | B12: 0.05 | C12: Cubre reparaciones, limpieza y riesgo de impago antes de la venta.
A13: Cuota Essentiel L'Essentiel (€/mes) | B13: 59 | C13: Del catálogo semzoprive.com
A14: Cuota Signature (€/mes) | B14: 149 | C14: Del catálogo semzoprive.com
A15: Cuota Privé (€/mes) | B15: 279 | C15: Del catálogo semzoprive.com
